pylint_super_not_called/__init__.py
pylint_super_not_called-0.10.2.dist-info/METADATA
pylint_super_not_called-0.10.2.dist-info/WHEEL
pylint_super_not_called-0.10.2.dist-info/licenses/LICENSE
pylint_super_not_called-0.10.2.dist-info/RECORD
