Metadata-Version: 2.1
Name: pylint_super_not_called
Version: 0.10.2
Summary: A Pylint plugin to ensure overloaded methods are calling the parent method with super
Project-URL: Homepage, https://github.com/prosehair/pylint_super_not_called_plugin
Project-URL: Bug Tracker, https://github.com/prosehair/pylint_super_not_called_plugin/issues
Author-email: Nicolas Mussat <nicolas@prose.com>
License-File: LICENSE
Classifier: License :: OSI Approved :: MIT License
Classifier: Operating System :: OS Independent
Classifier: Programming Language :: Python :: 3
Requires-Python: >=3.8
